[
  {
    "ContainingType": "SimpleProjectWebAPIwithDIandEF.Controllers.AccountController",
    "Method": "CheckRefreshToken",
    "RelativePath": "api/Account/Create-New-Jwt-BaseOn-Refresh-Token",
    "HttpMethod": "GET",
    "IsController": true,
    "Order": 0,
    "Parameters": [],
    "ReturnTypes": []
  },
  {
    "ContainingType": "SimpleProjectWebAPIwithDIandEF.Controllers.AccountController",
    "Method": "Login",
    "RelativePath": "api/Account/Login",
    "HttpMethod": "POST",
    "IsController": true,
    "Order": 0,
    "Parameters": [
      {
        "Name": "loginDTO",
        "Type": "App.Core.DTOs.IdentityDTO_s.LoginDTO",
        "IsRequired": true
      }
    ],
    "ReturnTypes": []
  },
  {
    "ContainingType": "SimpleProjectWebAPIwithDIandEF.Controllers.AccountController",
    "Method": "LogOut",
    "RelativePath": "api/Account/Logout",
    "HttpMethod": "GET",
    "IsController": true,
    "Order": 0,
    "Parameters": [],
    "ReturnTypes": []
  },
  {
    "ContainingType": "SimpleProjectWebAPIwithDIandEF.Controllers.AccountController",
    "Method": "Register",
    "RelativePath": "api/Account/Register",
    "HttpMethod": "POST",
    "IsController": true,
    "Order": 0,
    "Parameters": [
      {
        "Name": "userDTO",
        "Type": "App.Core.DTOs.IdentityDTO_s.RegisterDTO",
        "IsRequired": true
      }
    ],
    "ReturnTypes": [
      {
        "Type": "App.Core.Domain.IdentityModels.ApplicationUser",
        "MediaTypes": [
          "text/plain",
          "application/json",
          "text/json"
        ],
        "StatusCode": 200
      }
    ]
  },
  {
    "ContainingType": "SimpleProjectWebAPIwithDIandEF.Controllers.AccountController",
    "Method": "VerifyOTP",
    "RelativePath": "api/Account/Verify-OTP-Endpoint",
    "HttpMethod": "POST",
    "IsController": true,
    "Order": 0,
    "Parameters": [
      {
        "Name": "model",
        "Type": "App.Core.DTOs.IdentityDTO_s.VerifyOtpDto",
        "IsRequired": true
      }
    ],
    "ReturnTypes": []
  },
  {
    "ContainingType": "SimpleProjectWebAPIwithDIandEF.Controllers.RegionsController",
    "Method": "GetAll",
    "RelativePath": "api/Regions",
    "HttpMethod": "GET",
    "IsController": true,
    "Order": 0,
    "Parameters": [],
    "ReturnTypes": []
  },
  {
    "ContainingType": "SimpleProjectWebAPIwithDIandEF.Controllers.RegionsController",
    "Method": "AddRegion",
    "RelativePath": "api/Regions",
    "HttpMethod": "POST",
    "IsController": true,
    "Order": 0,
    "Parameters": [
      {
        "Name": "r",
        "Type": "App.Core.DTOs.RegionDTO_s.InputRegionDTO",
        "IsRequired": true
      }
    ],
    "ReturnTypes": []
  },
  {
    "ContainingType": "SimpleProjectWebAPIwithDIandEF.Controllers.RegionsController",
    "Method": "GetById",
    "RelativePath": "api/Regions/{id}",
    "HttpMethod": "GET",
    "IsController": true,
    "Order": 0,
    "Parameters": [
      {
        "Name": "id",
        "Type": "System.Guid",
        "IsRequired": true
      }
    ],
    "ReturnTypes": []
  },
  {
    "ContainingType": "SimpleProjectWebAPIwithDIandEF.Controllers.RegionsController",
    "Method": "updateRegion",
    "RelativePath": "api/Regions/{id}",
    "HttpMethod": "PUT",
    "IsController": true,
    "Order": 0,
    "Parameters": [
      {
        "Name": "id",
        "Type": "System.Guid",
        "IsRequired": true
      },
      {
        "Name": "r",
        "Type": "App.Core.DTOs.RegionDTO_s.InputRegionDTO",
        "IsRequired": true
      }
    ],
    "ReturnTypes": []
  },
  {
    "ContainingType": "SimpleProjectWebAPIwithDIandEF.Controllers.RegionsController",
    "Method": "DeleteRegion",
    "RelativePath": "api/Regions/{id}",
    "HttpMethod": "DELETE",
    "IsController": true,
    "Order": 0,
    "Parameters": [
      {
        "Name": "id",
        "Type": "System.Guid",
        "IsRequired": true
      }
    ],
    "ReturnTypes": []
  },
  {
    "ContainingType": "SimpleProjectWebAPIwithDIandEF.Controllers.RoadsController",
    "Method": "GetAllRoads",
    "RelativePath": "api/Roads",
    "HttpMethod": "GET",
    "IsController": true,
    "Order": 0,
    "Parameters": [
      {
        "Name": "DifficultyLevel",
        "Type": "System.String",
        "IsRequired": false
      },
      {
        "Name": "RoadLengthOrder",
        "Type": "System.String",
        "IsRequired": false
      },
      {
        "Name": "SearchByName",
        "Type": "System.String",
        "IsRequired": false
      }
    ],
    "ReturnTypes": []
  },
  {
    "ContainingType": "SimpleProjectWebAPIwithDIandEF.Controllers.RoadsController",
    "Method": "AddRoad",
    "RelativePath": "api/Roads",
    "HttpMethod": "POST",
    "IsController": true,
    "Order": 0,
    "Parameters": [
      {
        "Name": "addedRoad",
        "Type": "App.Core.DTOs.RoadDTO_s.InputRoadDTO",
        "IsRequired": true
      }
    ],
    "ReturnTypes": []
  },
  {
    "ContainingType": "SimpleProjectWebAPIwithDIandEF.Controllers.RoadsController",
    "Method": "GetRoadById",
    "RelativePath": "api/Roads/{id}",
    "HttpMethod": "GET",
    "IsController": true,
    "Order": 0,
    "Parameters": [
      {
        "Name": "id",
        "Type": "System.Guid",
        "IsRequired": true
      }
    ],
    "ReturnTypes": []
  },
  {
    "ContainingType": "SimpleProjectWebAPIwithDIandEF.Controllers.RoadsController",
    "Method": "UpdateRoad",
    "RelativePath": "api/Roads/{id}",
    "HttpMethod": "PUT",
    "IsController": true,
    "Order": 0,
    "Parameters": [
      {
        "Name": "id",
        "Type": "System.Guid",
        "IsRequired": true
      },
      {
        "Name": "addedRoad",
        "Type": "App.Core.DTOs.RoadDTO_s.InputRoadDTO",
        "IsRequired": true
      }
    ],
    "ReturnTypes": []
  },
  {
    "ContainingType": "SimpleProjectWebAPIwithDIandEF.Controllers.RoadsController",
    "Method": "DeleteRoad",
    "RelativePath": "api/Roads/{id}",
    "HttpMethod": "DELETE",
    "IsController": true,
    "Order": 0,
    "Parameters": [
      {
        "Name": "id",
        "Type": "System.Guid",
        "IsRequired": true
      }
    ],
    "ReturnTypes": []
  }
]